brewv/__init__.py
brewv/__main__.py
brewv/bottle.py
brewv/cli.py
brewv/constants.py
brewv/core.py
brewv/util.py
brew_versions-0.3.3.dist-info/LICENSE
brew_versions-0.3.3.dist-info/METADATA
brew_versions-0.3.3.dist-info/WHEEL
brew_versions-0.3.3.dist-info/entry_points.txt
brew_versions-0.3.3.dist-info/top_level.txt
brew_versions-0.3.3.dist-info/RECORD
